rtl/arbiter.v
module arbiter(
    input clk,
    input reset,
    input [3:0] req,
    output reg [3:0] grant,

    // APB Interface
    input PSEL,
    input PENABLE,
    input PWRITE,
    input [7:0] PADDR,
    input [31:0] PWDATA,
    output reg [31:0] PRDATA,
    output reg PREADY
);

// Arbitration logic
reg [1:0] pointer;
reg [1:0] next_pointer;

integer i;

// Aging logic 
reg [3:0] age_counter [3:0];
reg [3:0] age_limit_reg;
reg aged_request_found;
reg [1:0] aged_request;

// QoS scheduling
reg high_pri_found;
reg [1:0] high_pri_request;

reg [3:0] same_pri_req;
reg [1:0] highest_priority;
reg [2:0] congestion_threshold_reg;

//Congestion monitoring
reg [2:0] active_requests;
reg congestion;
reg [1:0] congestion_level;

//Performance counter
reg [31:0] total_requests;
reg [31:0] total_grants;
reg [31:0] starvation_events;
reg [31:0] qos_grants [3:0];
reg [1:0] priority_reg [3:0];



always @(posedge clk or posedge reset) begin
    if (reset) begin
        
        pointer <= 2'b00;
        
        total_requests    <= 0;
        total_grants      <= 0;
        starvation_events <= 0;

        qos_grants[0] <= 0;
        qos_grants[1] <= 0;
        qos_grants[2] <= 0;
        qos_grants[3] <= 0;

        
    //Configuration parameters
        age_limit_reg <= 4'd8;
        congestion_threshold_reg <= 3'd3;
    end
    else begin
        
        pointer <= next_pointer;

//--------------------------------------------------
// APB Counter Reset
//--------------------------------------------------
if (PSEL && PENABLE && PWRITE && PADDR == 8'h34)
begin
    total_requests    <= 0;
    total_grants      <= 0;
    starvation_events <= 0;

    qos_grants[0] <= 0;
    qos_grants[1] <= 0;
    qos_grants[2] <= 0;
    qos_grants[3] <= 0;
end

//--------------------------------------------------
// Normal Counter Updates
//--------------------------------------------------
else
begin
    total_requests <= total_requests + active_requests;

    if (grant != 4'b0000)
        total_grants <= total_grants + 1;

    if (aged_request_found)
        starvation_events <= starvation_events + 1;

    if (grant[0])
        qos_grants[0] <= qos_grants[0] + 1;

    if (grant[1])
        qos_grants[1] <= qos_grants[1] + 1;

    if (grant[2])
        qos_grants[2] <= qos_grants[2] + 1;

    if (grant[3])
        qos_grants[3] <= qos_grants[3] + 1;
end
        
       
    end
end

always @(*) begin
    grant = 4'b0000;
    next_pointer = pointer;
    active_requests = 0;
    congestion = 0;
    congestion_level = 2'b00;
    PREADY = 1'b1;

        // Count active requests
    if (req[0])
        active_requests = active_requests + 1;

    if (req[1])
        active_requests = active_requests + 1;

    if (req[2])
        active_requests = active_requests + 1;

    if (req[3])
        active_requests = active_requests + 1;

    // Check congestion
    if (active_requests >= congestion_threshold_reg)
        congestion = 1;
    
    // Determine congestion level
    if (active_requests <= 1)
        congestion_level = 2'b00;      // Low
    else if (active_requests <= 3)
        congestion_level = 2'b01;      // Medium
    else
        congestion_level = 2'b10;      // High


    // Grant to the aged request
    if(aged_request_found && req[aged_request])
    begin
        case(aged_request)

        2'd0:
        begin
            grant = 4'b0001;
            next_pointer = 2'd1;
        end

        2'd1:
        begin
            grant = 4'b0010;
            next_pointer = 2'd2;
        end

        2'd2:
        begin
            grant = 4'b0100;
            next_pointer = 2'd3;
        end

        2'd3:
        begin
            grant = 4'b1000;
            next_pointer = 2'd0;
        end

        endcase
    end

    else if (high_pri_found)
    begin
        

    case(pointer)

2'd0:
begin
    if(same_pri_req[0])
    begin
        grant = 4'b0001;
        next_pointer = 2'd1;
    end
    else if(same_pri_req[1])
    begin
        grant = 4'b0010;
        next_pointer = 2'd2;
    end
    else if(same_pri_req[2])
    begin
        grant = 4'b0100;
        next_pointer = 2'd3;
    end
    else if(same_pri_req[3])
    begin
        grant = 4'b1000;
        next_pointer = 2'd0;
    end
end
    

2'd1:
begin
    if(same_pri_req[1])
    begin
        grant = 4'b0010;
        next_pointer = 2'd2;
    end
    else if(same_pri_req[2])
    begin
        grant = 4'b0100;
        next_pointer = 2'd3;
    end
    else if(same_pri_req[3])
    begin
        grant = 4'b1000;
        next_pointer = 2'd0;
    end
    else if(same_pri_req[0])
    begin
        grant = 4'b0001;
        next_pointer = 2'd1;
    end
end

2'd2:
begin
    if(same_pri_req[2])
    begin
        grant = 4'b0100;
        next_pointer = 2'd3;
    end
    else if(same_pri_req[3])
    begin
        grant = 4'b1000;
        next_pointer = 2'd0;
    end
    else if(same_pri_req[0])
    begin
        grant = 4'b0001;
        next_pointer = 2'd1;
    end
    else if(same_pri_req[1])
    begin
        grant = 4'b0010;
        next_pointer = 2'd2;
    end
end

2'd3:
begin
    if(same_pri_req[3])
    begin
        grant = 4'b1000;
        next_pointer = 2'd0;
    end
    else if(same_pri_req[0])
    begin
        grant = 4'b0001;
        next_pointer = 2'd1;
    end
    else if(same_pri_req[1])
    begin
        grant = 4'b0010;
        next_pointer = 2'd2;
    end
    else if(same_pri_req[2])
    begin
        grant = 4'b0100;
        next_pointer = 2'd3;
    end
end

default:
begin
    grant = 4'b0000;
    next_pointer = 2'd0;
end

    endcase
    
end
end

always @(posedge clk or posedge reset)
begin
    if(reset)
    begin
        for(i=0; i<4; i=i+1)
            age_counter[i] <= 4'd0;
        
        priority_reg[0] <= 2'd3;
        priority_reg[1] <= 2'd2;
        priority_reg[2] <= 2'd1;
        priority_reg[3] <= 2'd0;
    end
    else
    begin
        for(i=0; i<4; i=i+1)
        begin
            if(req[i] && !grant[i])
                age_counter[i] <= age_counter[i] + 1'b1;

            else
                age_counter[i] <= 4'd0;
        end

        if (PSEL && PENABLE && PWRITE)
        begin
            case (PADDR)
            8'h00:
                priority_reg[0] <= PWDATA[1:0];

            8'h04:
                priority_reg[1] <= PWDATA[1:0];

            8'h08:
                priority_reg[2] <= PWDATA[1:0];

            8'h0C:
                priority_reg[3] <= PWDATA[1:0];

            8'h10:
                age_limit_reg <= PWDATA[3:0];

            8'h14:
                congestion_threshold_reg <= PWDATA[2:0];

            default:
            begin
            end
            endcase
        end
    end
end

always @(*) begin

    aged_request_found = 1'b0;
    aged_request = 2'd0;

    // Start with requester 0

    if(req[0] && age_counter[0] >= age_limit_reg)
    begin
        aged_request_found = 1'b1;
        aged_request = 2'd0;
    end

    // Compare requester 1

    if(req[1] &&
       age_counter[1] >= age_limit_reg &&
       (!aged_request_found ||
        age_counter[1] > age_counter[aged_request]))
    begin
        aged_request_found = 1'b1;
        aged_request = 2'd1;
    end

    // Compare requester 2

    if(req[2] &&
       age_counter[2] >= age_limit_reg &&
       (!aged_request_found ||
        age_counter[2] > age_counter[aged_request]))
    begin
        aged_request_found = 1'b1;
        aged_request = 2'd2;
    end

    // Compare requester 3

    if(req[3] &&
       age_counter[3] >= age_limit_reg &&
       (!aged_request_found ||
        age_counter[3] > age_counter[aged_request]))
    begin
        aged_request_found = 1'b1;
        aged_request = 2'd3;
    end

end

always @(*) begin

    high_pri_found = 1'b0;
    high_pri_request = 2'd0;
    highest_priority = 2'd0;

    // Check requester 0

    if(req[0])
    begin
        high_pri_found = 1'b1;
        high_pri_request = 2'd0;
        highest_priority = priority_reg[0];
    end

    // Compare requester 1

    if(req[1] &&
       (!high_pri_found ||
        priority_reg[1] > highest_priority))
    begin
        high_pri_found = 1'b1;
        high_pri_request = 2'd1;
        highest_priority = priority_reg[1];
    end

    // Compare requester 2

    if(req[2] &&
       (!high_pri_found ||
        priority_reg[2] > highest_priority))
    begin
        high_pri_found = 1'b1;
        high_pri_request = 2'd2;
        highest_priority = priority_reg[2];
    end

    // Compare requester 3

    if(req[3] &&
       (!high_pri_found ||
        priority_reg[3] > highest_priority))
    begin
        high_pri_found = 1'b1;
        high_pri_request = 2'd3;
        highest_priority = priority_reg[3];
    end

end

always @(*) begin

    same_pri_req = 4'b0000;

    if(req[0] && priority_reg[0] == highest_priority)
        same_pri_req[0] = 1'b1;

    if(req[1] && priority_reg[1] == highest_priority)
        same_pri_req[1] = 1'b1;

    if(req[2] && priority_reg[2] == highest_priority)
        same_pri_req[2] = 1'b1;

    if(req[3] && priority_reg[3] == highest_priority)
        same_pri_req[3] = 1'b1;

end

//==============================================================================
// APB Slave Interface
//==============================================================================
always @(*) begin
    PRDATA = 32'd0;

    if (PSEL && PENABLE && !PWRITE) begin
        case (PADDR)
8'h00:
    PRDATA = {30'd0, priority_reg[0]};

8'h04:
    PRDATA = {30'd0, priority_reg[1]};

8'h08:
    PRDATA = {30'd0, priority_reg[2]};

8'h0C:
    PRDATA = {30'd0, priority_reg[3]};

8'h10:
    PRDATA = {28'd0, age_limit_reg};

8'h14:
    PRDATA = {29'd0, congestion_threshold_reg};

8'h18:
    PRDATA = total_requests;

8'h1C:
    PRDATA = total_grants;

8'h20:
    PRDATA = starvation_events;

8'h24:
    PRDATA = qos_grants[0];

8'h28:
    PRDATA = qos_grants[1];

8'h2C:
    PRDATA = qos_grants[2];

8'h30:
    PRDATA = qos_grants[3];

default:
    PRDATA = 32'd0;
        endcase
    end
end

endmodule

tb/tb_apb_write.v
`timescale 1ns/1ps

module tb_apb_write;

reg clk;
reg reset;
reg [3:0] req;

reg PSEL;
reg PENABLE;
reg PWRITE;
reg [7:0] PADDR;
reg [31:0] PWDATA;

wire [3:0] grant;
wire [31:0] PRDATA;
wire PREADY;

arbiter DUT (
    .clk(clk),
    .reset(reset),
    .req(req),
    .grant(grant),

    .PSEL(PSEL),
    .PENABLE(PENABLE),
    .PWRITE(PWRITE),
    .PADDR(PADDR),
    .PWDATA(PWDATA),
    .PRDATA(PRDATA),
    .PREADY(PREADY)
);

//--------------------------------------------------
// Clock Generation
//--------------------------------------------------
initial begin
    clk = 0;
    forever #5 clk = ~clk;
end

//--------------------------------------------------
// APB Write Task
//--------------------------------------------------
task apb_write;
    input [7:0] addr;
    input [31:0] data;
begin

    @(posedge clk);
    PSEL    <= 1'b1;
    PENABLE <= 1'b0;
    PWRITE  <= 1'b1;
    PADDR   <= addr;
    PWDATA  <= data;

    @(posedge clk);
    PENABLE <= 1'b1;

    @(posedge clk);
    PSEL    <= 1'b0;
    PENABLE <= 1'b0;
    PWRITE  <= 1'b0;
    PADDR   <= 8'h00;
    PWDATA  <= 32'h00000000;

end
endtask

//--------------------------------------------------
// Waveform Dump
//--------------------------------------------------
initial begin
    $dumpfile("apb_write.vcd");
    $dumpvars(0, tb_apb_write);
end

//--------------------------------------------------
// Test Sequence
//--------------------------------------------------
initial begin

    reset   = 1'b1;
    req     = 4'b0000;

    PSEL    = 0;
    PENABLE = 0;
    PWRITE  = 0;
    PADDR   = 0;
    PWDATA  = 0;

    #20;
    reset = 0;

    // Program QoS Priorities
    apb_write(8'h00, 32'd3);
    apb_write(8'h04, 32'd2);
    apb_write(8'h08, 32'd1);
    apb_write(8'h0C, 32'd0);

    // Program Age Limit
    apb_write(8'h10, 32'd8);

    // Program Congestion Threshold
    apb_write(8'h14, 32'd3);

    #40;

    $finish;

end

//--------------------------------------------------
// Console Monitor
//--------------------------------------------------
initial begin
    $display("---------------------------------------------------------------");
    $display(" Time    PSEL PENABLE PWRITE   PADDR     PWDATA        PREADY");
    $display("---------------------------------------------------------------");

    $monitor("%5t      %b      %b       %b     0x%02h   0x%08h     %b",
        $time,
        PSEL,
        PENABLE,
        PWRITE,
        PADDR,
        PWDATA,
        PREADY);
end

endmodule

waveforms/apb_write.vcd
$date
	Tue Jul 07 18:40:03 2026
$end
$version
	Icarus Verilog
$end
$timescale
	1ps
$end
$scope module tb_apb_write $end
$var wire 4 ! grant [3:0] $end
$var wire 1 " PREADY $end
$var wire 32 # PRDATA [31:0] $end
$var reg 8 $ PADDR [7:0] $end
$var reg 1 % PENABLE $end
$var reg 1 & PSEL $end
$var reg 32 ' PWDATA [31:0] $end
$var reg 1 ( PWRITE $end
$var reg 1 ) clk $end
$var reg 4 * req [3:0] $end
$var reg 1 + reset $end
$scope module DUT $end
$var wire 8 , PADDR [7:0] $end
$var wire 1 % PENABLE $end
$var wire 1 & PSEL $end
$var wire 32 - PWDATA [31:0] $end
$var wire 1 ( PWRITE $end
$var wire 1 ) clk $end
$var wire 4 . req [3:0] $end
$var wire 1 + reset $end
$var reg 32 / PRDATA [31:0] $end
$var reg 1 " PREADY $end
$var reg 3 0 active_requests [2:0] $end
$var reg 4 1 age_limit_reg [3:0] $end
$var reg 2 2 aged_request [1:0] $end
$var reg 1 3 aged_request_found $end
$var reg 1 4 congestion $end
$var reg 2 5 congestion_level [1:0] $end
$var reg 3 6 congestion_threshold_reg [2:0] $end
$var reg 4 7 grant [3:0] $end
$var reg 1 8 high_pri_found $end
$var reg 2 9 high_pri_request [1:0] $end
$var reg 2 : highest_priority [1:0] $end
$var reg 2 ; next_pointer [1:0] $end
$var reg 2 < pointer [1:0] $end
$var reg 4 = same_pri_req [3:0] $end
$var reg 32 > starvation_events [31:0] $end
$var reg 32 ? total_grants [31:0] $end
$var reg 32 @ total_requests [31:0] $end
$var integer 32 A i [31:0] $end
$upscope $end
$scope task apb_write $end
$var reg 8 B addr [7:0] $end
$var reg 32 C data [31:0] $end
$upscope $end
$upscope $end
$enddefinitions $end
$comment Show the parameter values. $end
$dumpall
$end
#0
$dumpvars
bx C
bx B
b100 A
b0 @
b0 ?
b0 >
b0 =
b0 <
b0 ;
b0 :
b0 9
08
b0 7
b11 6
b0 5
04
03
b0 2
b1000 1
b0 0
b0 /
b0 .
b0 -
b0 ,
1+
b0 *
0)
0(
b0 '
0&
0%
b0 $
b0 #
1"
b0 !
$end
#5000
b100 A
1)
#10000
0)
#15000
b100 A
1)
#20000
0)
b11 C
b0 B
0+
#25000
b11 '
b11 -
1(
1&
b100 A
1)
#30000
0)
#35000
1%
b100 A
1)
#40000
0)
#45000
b0 '
b0 -
0(
0%
0&
b100 A
b10 C
b100 B
1)
#50000
0)
#55000
b10 '
b10 -
b100 $
b100 ,
1(
1&
b100 A
1)
#60000
0)
#65000
1%
b100 A
1)
#70000
0)
#75000
b0 '
b0 -
b0 $
b0 ,
0(
0%
0&
b100 A
b1 C
b1000 B
1)
#80000
0)
#85000
b1 '
b1 -
b1000 $
b1000 ,
1(
1&
b100 A
1)
#90000
0)
#95000
1%
b100 A
1)
#100000
0)
#105000
b0 '
b0 -
b0 $
b0 ,
0(
0%
0&
b100 A
b0 C
b1100 B
1)
#110000
0)
#115000
b1100 $
b1100 ,
1(
1&
b100 A
1)
#120000
0)
#125000
1%
b100 A
1)
#130000
0)
#135000
b0 $
b0 ,
0(
0%
0&
b100 A
b1000 C
b10000 B
1)
#140000
0)
#145000
b1000 '
b1000 -
b10000 $
b10000 ,
1(
1&
b100 A
1)
#150000
0)
#155000
1%
b100 A
1)
#160000
0)
#165000
b0 '
b0 -
b0 $
b0 ,
0(
0%
0&
b100 A
b11 C
b10100 B
1)
#170000
0)
#175000
b11 '
b11 -
b10100 $
b10100 ,
1(
1&
b100 A
1)
#180000
0)
#185000
1%
b100 A
1)
#190000
0)
#195000
b0 '
b0 -
b0 $
b0 ,
0(
0%
0&
b100 A
1)
#200000
0)
#205000
b100 A
1)
#210000
0)
#215000
b100 A
1)
#220000
0)
#225000
b100 A
1)
#230000
0)
#235000
b100 A
1)
